{
  "original_file": "Sweden_1994.csv",
  "year": 1994,
  "country": "SE",
  "var": "ed_isced_0to2_m_35to44",
  "data": {
    "1440": {
      "%": 66.108788,
      "v": 1106
    },
    "1489": {
      "%": 58.96785,
      "v": 1394
    },
    "0764": {
      "%": 68.402779,
      "v": 985
    },
    "0604": {
      "%": 71.0,
      "v": 355
    },
    "1984": {
      "%": 63.696369,
      "v": 579
    },
    "1784": {
      "%": 68.138084,
      "v": 1204
    },
    "1882": {
      "%": 74.494949,
      "v": 590
    },
    "2084": {
      "%": 65.973869,
      "v": 1111
    },
    "1460": {
      "%": 78.796173,
      "v": 576
    },
    "2326": {
      "%": 78.221413,
      "v": 431
    },
    "2403": {
      "%": 71.069183,
      "v": 113
    },
    "1260": {
      "%": 73.846153,
      "v": 720
    },
    "2582": {
      "%": 54.974781,
      "v": 1199
    },
    "1443": {
      "%": 63.966942,
      "v": 387
    },
    "2183": {
      "%": 69.032257,
      "v": 1284
    },
    "0885": {
      "%": 73.291138,
      "v": 579
    },
    "2081": {
      "%": 64.206978,
      "v": 2097
    },
    "1490": {
      "%": 63.959393,
      "v": 4032
    },
    "0127": {
      "%": 61.675179,
      "v": 3019
    },
    "0560": {
      "%": 74.242424,
      "v": 294
    },
    "1272": {
      "%": 72.992699,
      "v": 600
    },
    "2305": {
      "%": 75.139145,
      "v": 405
    },
    "1231": {
      "%": 63.279678,
      "v": 629
    },
    "1278": {
      "%": 63.605053,
      "v": 554
    },
    "1438": {
      "%": 77.842567,
      "v": 267
    },
    "0162": {
      "%": 18.665159,
      "v": 330
    },
    "1862": {
      "%": 69.904243,
      "v": 511
    },
    "2425": {
      "%": 77.307693,
      "v": 201
    },
    "1730": {
      "%": 75.625,
      "v": 484
    },
    "0125": {
      "%": 48.549725,
      "v": 703
    },
    "0686": {
      "%": 61.69355,
      "v": 765
    },
    "0862": {
      "%": 72.690216,
      "v": 535
    },
    "0381": {
      "%": 63.379143,
      "v": 1568
    },
    "0484": {
      "%": 63.906792,
      "v": 3867
    },
    "1285": {
      "%": 62.327717,
      "v": 1221
    },
    "1445": {
      "%": 76.832153,
      "v": 325
    },
    "1982": {
      "%": 71.345032,
      "v": 610
    },
    "1382": {
      "%": 69.545105,
      "v": 1804
    },
    "1499": {
      "%": 68.064827,
      "v": 1428
    },
    "2080": {
      "%": 55.221195,
      "v": 2147
    },
    "1782": {
      "%": 74.673012,
      "v": 628
    },
    "0562": {
      "%": 56.726307,
      "v": 856
    },
    "0482": {
      "%": 69.224281,
      "v": 821
    },
    "1763": {
      "%": 65.746552,
      "v": 524
    },
    "1439": {
      "%": 74.018692,
      "v": 396
    },
    "2026": {
      "%": 63.936783,
      "v": 445
    },
    "0662": {
      "%": 69.525192,
      "v": 1435
    },
    "0461": {
      "%": 64.133736,
      "v": 422
    },
    "0617": {
      "%": 76.08371,
      "v": 509
    },
    "0980": {
      "%": 67.929054,
      "v": 2834
    },
    "1764": {
      "%": 80.267059,
      "v": 541
    },
    "1444": {
      "%": 71.226418,
      "v": 302
    },
    "1447": {
      "%": 77.924942,
      "v": 353
    },
    "2523": {
      "%": 68.860161,
      "v": 1172
    },
    "2180": {
      "%": 63.390503,
      "v": 3844
    },
    "1480": {
      "%": 47.668125,
      "v": 14800
    },
    "1471": {
      "%": 74.411461,
      "v": 727
    },
    "0643": {
      "%": 67.391304,
      "v": 465
    },
    "1783": {
      "%": 74.121094,
      "v": 759
    },
    "1861": {
      "%": 64.792389,
      "v": 749
    },
    "1961": {
      "%": 67.981224,
      "v": 724
    },
    "1380": {
      "%": 59.188633,
      "v": 3166
    },
    "1761": {
      "%": 48.448277,
      "v": 562
    },
    "0136": {
      "%": 59.59264,
      "v": 2721
    },
    "2583": {
      "%": 72.24939,
      "v": 591
    },
    "0331": {
      "%": 77.788948,
      "v": 774
    },
    "2083": {
      "%": 66.405571,
      "v": 763
    },
    "1283": {
      "%": 57.171234,
      "v": 4317
    },
    "1466": {
      "%": 74.307693,
      "v": 483
    },
    "1497": {
      "%": 64.444443,
      "v": 406
    },
    "2104": {
      "%": 73.664124,
      "v": 579
    },
    "0126": {
      "%": 54.454437,
      "v": 3209
    },
    "2184": {
      "%": 69.127518,
      "v": 1854
    },
    "0860": {
      "%": 78.272728,
      "v": 861
    },
    "1315": {
      "%": 74.099724,
      "v": 535
    },
    "1863": {
      "%": 66.176468,
      "v": 360
    },
    "2361": {
      "%": 77.93367,
      "v": 611
    },
    "2280": {
      "%": 59.613129,
      "v": 1017
    },
    "1401": {
      "%": 51.23428,
      "v": 1100
    },
    "1293": {
      "%": 64.299423,
      "v": 2010
    },
    "0305": {
      "%": 59.310986,
      "v": 637
    },
    "1284": {
      "%": 53.33783,
      "v": 791
    },
    "0821": {
      "%": 72.670807,
      "v": 351
    },
    "1266": {
      "%": 70.031219,
      "v": 673
    },
    "1267": {
      "%": 61.889927,
      "v": 596
    },
    "0123": {
      "%": 49.758083,
      "v": 1954
    },
    "0680": {
      "%": 60.222942,
      "v": 4268
    },
    "2514": {
      "%": 71.720345,
      "v": 913
    },
    "0880": {
      "%": 57.471867,
      "v": 2196
    },
    "1446": {
      "%": 67.65873,
      "v": 341
    },
    "1082": {
      "%": 67.019669,
      "v": 1329
    },
    "1883": {
      "%": 62.875122,
      "v": 1299
    },
    "1080": {
      "%": 57.051117,
      "v": 2221
    },
    "1780": {
      "%": 54.485947,
      "v": 2830
    },
    "0483": {
      "%": 65.292252,
      "v": 1441
    },
    "1715": {
      "%": 65.388954,
      "v": 580
    },
    "0513": {
      "%": 70.116615,
      "v": 481
    },
    "2584": {
      "%": 58.885384,
      "v": 1120
    },
    "1276": {
      "%": 70.165749,
      "v": 762
    },
    "2282": {
      "%": 70.790817,
      "v": 1110
    },
    "1290": {
      "%": 58.920383,
      "v": 2827
    },
    "1781": {
      "%": 66.860466,
      "v": 1150
    },
    "2309": {
      "%": 63.636364,
      "v": 686
    },
    "1881": {
      "%": 64.913658,
      "v": 827
    },
    "1384": {
      "%": 50.643276,
      "v": 2165
    },
    "1960": {
      "%": 65.432098,
      "v": 371
    },
    "1482": {
      "%": 57.811195,
      "v": 1384
    },
    "1261": {
      "%": 56.389065,
      "v": 887
    },
    "1983": {
      "%": 68.870056,
      "v": 1219
    },
    "1381": {
      "%": 73.324821,
      "v": 1149
    },
    "1282": {
      "%": 57.417801,
      "v": 1432
    },
    "1860": {
      "%": 72.689079,
      "v": 346
    },
    "1814": {
      "%": 73.022316,
      "v": 360
    },
    "2029": {
      "%": 65.025124,
      "v": 647
    },
    "1441": {
      "%": 52.076675,
      "v": 1304
    },
    "0761": {
      "%": 74.265976,
      "v": 430
    },
    "0186": {
      "%": 28.447596,
      "v": 722
    },
    "1494": {
      "%": 65.790558,
      "v": 1602
    },
    "1462": {
      "%": 74.450264,
      "v": 711
    },
    "1885": {
      "%": 68.920525,
      "v": 1162
    },
    "0580": {
      "%": 46.195526,
      "v": 4007
    },
    "0781": {
      "%": 70.445793,
      "v": 1280
    },
    "2161": {
      "%": 76.120499,
      "v": 1036
    },
    "1864": {
      "%": 77.47525,
      "v": 313
    },
    "1262": {
      "%": 39.099735,
      "v": 443
    },
    "2085": {
      "%": 65.104744,
      "v": 1181
    },
    "2580": {
      "%": 52.762753,
      "v": 2731
    },
    "1281": {
      "%": 29.761009,
      "v": 1980
    },
    "2481": {
      "%": 65.608467,
      "v": 620
    },
    "1484": {
      "%": 68.761551,
      "v": 744
    },
    "1280": {
      "%": 53.745731,
      "v": 8810
    },
    "2023": {
      "%": 75.342468,
      "v": 605
    },
    "2418": {
      "%": 78.498291,
      "v": 230
    },
    "1493": {
      "%": 64.774948,
      "v": 993
    },
    "1463": {
      "%": 71.045692,
      "v": 1617
    },
    "0767": {
      "%": 73.991028,
      "v": 495
    },
    "1461": {
      "%": 73.855247,
      "v": 500
    },
    "0586": {
      "%": 67.45256,
      "v": 1173
    },
    "2062": {
      "%": 67.536034,
      "v": 984
    },
    "0583": {
      "%": 65.235176,
      "v": 1914
    },
    "0642": {
      "%": 64.682541,
      "v": 326
    },
    "1430": {
      "%": 72.837837,
      "v": 539
    },
    "1762": {
      "%": 67.025093,
      "v": 187
    },
    "1481": {
      "%": 49.726776,
      "v": 1911
    },
    "0861": {
      "%": 72.043015,
      "v": 670
    },
    "0840": {
      "%": 68.404259,
      "v": 643
    },
    "0182": {
      "%": 39.442616,
      "v": 2038
    },
    "1884": {
      "%": 67.601685,
      "v": 482
    },
    "1962": {
      "%": 70.588234,
      "v": 348
    },
    "2132": {
      "%": 76.997246,
      "v": 559
    },
    "2401": {
      "%": 67.594437,
      "v": 340
    },
    "0581": {
      "%": 61.720562,
      "v": 5058
    },
    "0188": {
      "%": 67.237617,
      "v": 2159
    },
    "2417": {
      "%": 74.229691,
      "v": 265
    },
    "0881": {
      "%": 74.410027,
      "v": 1009
    },
    "0480": {
      "%": 60.11961,
      "v": 1910
    },
    "0192": {
      "%": 62.977345,
      "v": 973
    },
    "0682": {
      "%": 67.951927,
      "v": 1357
    },
    "2101": {
      "%": 76.569038,
      "v": 366
    },
    "1060": {
      "%": 73.733192,
      "v": 713
    },
    "2034": {
      "%": 71.511627,
      "v": 369
    },
    "1421": {
      "%": 66.259399,
      "v": 705
    },
    "1273": {
      "%": 71.128319,
      "v": 643
    },
    "0882": {
      "%": 67.538376,
      "v": 1188
    },
    "2121": {
      "%": 77.419357,
      "v": 720
    },
    "0481": {
      "%": 63.44994,
      "v": 526
    },
    "2521": {
      "%": 75.041878,
      "v": 448
    },
    "1402": {
      "%": 48.442169,
      "v": 1135
    },
    "1275": {
      "%": 69.582504,
      "v": 350
    },
    "2581": {
      "%": 65.275345,
      "v": 1861
    },
    "2303": {
      "%": 72.845955,
      "v": 279
    },
    "2409": {
      "%": 68.495575,
      "v": 387
    },
    "1081": {
      "%": 67.542419,
      "v": 1234
    },
    "2031": {
      "%": 70.349648,
      "v": 503
    },
    "1981": {
      "%": 66.645203,
      "v": 1035
    },
    "0128": {
      "%": 53.7859,
      "v": 412
    },
    "2181": {
      "%": 65.834633,
      "v": 1688
    },
    "0191": {
      "%": 58.584072,
      "v": 1324
    },
    "1291": {
      "%": 66.301796,
      "v": 848
    },
    "1265": {
      "%": 71.31295,
      "v": 793
    },
    "1495": {
      "%": 65.016777,
      "v": 775
    },
    "2482": {
      "%": 61.576447,
      "v": 3242
    },
    "1904": {
      "%": 73.654388,
      "v": 260
    },
    "1264": {
      "%": 65.981499,
      "v": 642
    },
    "1496": {
      "%": 60.030487,
      "v": 1969
    },
    "2061": {
      "%": 71.597,
      "v": 668
    },
    "2283": {
      "%": 67.896011,
      "v": 1123
    },
    "0163": {
      "%": 38.346241,
      "v": 1535
    },
    "0184": {
      "%": 42.911682,
      "v": 1686
    },
    "2422": {
      "%": 76.818184,
      "v": 169
    },
    "1427": {
      "%": 69.710808,
      "v": 458
    },
    "1230": {
      "%": 52.491962,
      "v": 653
    },
    "1415": {
      "%": 59.548977,
      "v": 845
    },
    "0180": {
      "%": 40.582458,
      "v": 21822
    },
    "1760": {
      "%": 69.421486,
      "v": 252
    },
    "2421": {
      "%": 76.92308,
      "v": 400
    },
    "0486": {
      "%": 59.582245,
      "v": 1141
    },
    "1486": {
      "%": 65.633072,
      "v": 508
    },
    "2313": {
      "%": 77.38446,
      "v": 787
    },
    "0183": {
      "%": 51.337997,
      "v": 1247
    },
    "2281": {
      "%": 60.99752,
      "v": 3938
    },
    "1766": {
      "%": 71.213745,
      "v": 663
    },
    "1907": {
      "%": 68.698708,
      "v": 586
    },
    "1214": {
      "%": 62.998791,
      "v": 521
    },
    "1263": {
      "%": 60.850113,
      "v": 816
    },
    "1465": {
      "%": 79.110512,
      "v": 587
    },
    "1785": {
      "%": 68.959274,
      "v": 762
    },
    "2082": {
      "%": 70.488083,
      "v": 621
    },
    "0684": {
      "%": 75.226974,
      "v": 580
    },
    "2182": {
      "%": 72.845688,
      "v": 1454
    },
    "0582": {
      "%": 64.705879,
      "v": 660
    },
    "0181": {
      "%": 62.26759,
      "v": 3416
    },
    "1083": {
      "%": 73.227615,
      "v": 785
    },
    "1435": {
      "%": 70.273628,
      "v": 565
    },
    "1472": {
      "%": 73.404259,
      "v": 552
    },
    "1498": {
      "%": 71.839081,
      "v": 625
    },
    "0360": {
      "%": 76.381531,
      "v": 1009
    },
    "2262": {
      "%": 72.362206,
      "v": 919
    },
    "0763": {
      "%": 73.375259,
      "v": 700
    },
    "1419": {
      "%": 60.990101,
      "v": 616
    },
    "1270": {
      "%": 73.483948,
      "v": 618
    },
    "1737": {
      "%": 73.716011,
      "v": 732
    },
    "0834": {
      "%": 71.057884,
      "v": 356
    },
    "1452": {
      "%": 73.448273,
      "v": 639
    },
    "0687": {
      "%": 69.016701,
      "v": 744
    },
    "1287": {
      "%": 64.760002,
      "v": 1619
    },
    "1488": {
      "%": 62.562954,
      "v": 2236
    },
    "0488": {
      "%": 61.72662,
      "v": 429
    },
    "0138": {
      "%": 53.682896,
      "v": 1290
    },
    "0160": {
      "%": 29.056696,
      "v": 1189
    },
    "1473": {
      "%": 75.521561,
      "v": 543
    },
    "1485": {
      "%": 60.604172,
      "v": 1946
    },
    "1491": {
      "%": 69.036842,
      "v": 1068
    },
    "2480": {
      "%": 47.160316,
      "v": 3280
    },
    "0114": {
      "%": 55.546753,
      "v": 1402
    },
    "0139": {
      "%": 55.676857,
      "v": 765
    },
    "0380": {
      "%": 41.638462,
      "v": 5413
    },
    "0760": {
      "%": 73.953491,
      "v": 477
    },
    "0584": {
      "%": 65.360825,
      "v": 317
    },
    "0665": {
      "%": 73.949577,
      "v": 616
    },
    "0563": {
      "%": 73.366837,
      "v": 438
    },
    "0115": {
      "%": 53.376778,
      "v": 901
    },
    "2021": {
      "%": 79.475983,
      "v": 364
    },
    "1470": {
      "%": 75.369888,
      "v": 866
    },
    "1383": {
      "%": 65.770309,
      "v": 2348
    },
    "0187": {
      "%": 42.756184,
      "v": 242
    },
    "1233": {
      "%": 46.516293,
      "v": 928
    },
    "0685": {
      "%": 71.562157,
      "v": 1301
    },
    "2462": {
      "%": 71.824104,
      "v": 441
    },
    "0884": {
      "%": 74.881065,
      "v": 787
    },
    "2404": {
      "%": 70.862473,
      "v": 304
    },
    "0428": {
      "%": 73.632538,
      "v": 525
    },
    "1487": {
      "%": 62.314049,
      "v": 1508
    },
    "2460": {
      "%": 59.805511,
      "v": 369
    },
    "0120": {
      "%": 54.563393,
      "v": 1106
    },
    "0683": {
      "%": 67.92453,
      "v": 1476
    },
    "0883": {
      "%": 68.042038,
      "v": 1748
    },
    "1980": {
      "%": 51.081371,
      "v": 4275
    },
    "0780": {
      "%": 53.172775,
      "v": 2539
    },
    "1442": {
      "%": 72.829132,
      "v": 520
    },
    "0512": {
      "%": 74.551971,
      "v": 208
    },
    "1286": {
      "%": 62.470024,
      "v": 1042
    },
    "0765": {
      "%": 64.305176,
      "v": 708
    },
    "2039": {
      "%": 79.755669,
      "v": 457
    },
    "0319": {
      "%": 75.401932,
      "v": 469
    },
    "2560": {
      "%": 73.230766,
      "v": 476
    },
    "1292": {
      "%": 59.788826,
      "v": 1359
    },
    "1492": {
      "%": 65.945328,
      "v": 579
    },
    "2260": {
      "%": 69.570404,
      "v": 583
    },
    "2321": {
      "%": 67.626884,
      "v": 493
    },
    "1765": {
      "%": 76.92308,
      "v": 510
    },
    "2463": {
      "%": 66.666664,
      "v": 172
    },
    "1277": {
      "%": 71.412926,
      "v": 652
    },
    "0561": {
      "%": 64.216866,
      "v": 533
    },
    "1407": {
      "%": 61.391541,
      "v": 450
    },
    "0509": {
      "%": 74.655647,
      "v": 271
    },
    "1880": {
      "%": 54.887508,
      "v": 4245
    },
    "1257": {
      "%": 73.255814,
      "v": 441
    },
    "2284": {
      "%": 69.33165,
      "v": 2749
    },
    "2380": {
      "%": 55.504696,
      "v": 2304
    },
    "0117": {
      "%": 50.0,
      "v": 1106
    },
    "0382": {
      "%": 69.035202,
      "v": 1059
    },
    "1256": {
      "%": 72.606926,
      "v": 713
    },
    "2518": {
      "%": 72.881355,
      "v": 344
    }
  }
}