{
  "original_file": "Finland_2002.csv",
  "year": 2002,
  "country": "FI",
  "var": "ed_isced_6to8_f_65plus",
  "data": {
    "020": {
      "%": 2.7057498,
      "v": 48.0
    },
    "005": {
      "%": 3.5714285,
      "v": 42.0
    },
    "009": {
      "%": 2.6022305,
      "v": 7.0
    },
    "010": {
      "%": 2.108222,
      "v": 30.0
    },
    "016": {
      "%": 4.7434654,
      "v": 49.0
    },
    "018": {
      "%": 3.5175879,
      "v": 14.0
    },
    "019": {
      "%": 3.4129694,
      "v": 10.0
    },
    "035": {
      "%": 6.7796612,
      "v": 4.0
    },
    "043": {
      "%": 2.3255813,
      "v": 2.0
    },
    "046": {
      "%": 3.2128515,
      "v": 8.0
    },
    "047": {
      "%": 2.7027028,
      "v": 5.0
    },
    "049": {
      "%": 15.052532,
      "v": 2235.0
    },
    "050": {
      "%": 2.9974489,
      "v": 47.0
    },
    "051": {
      "%": 4.0858016,
      "v": 40.0
    },
    "052": {
      "%": 3.8690476,
      "v": 13.0
    },
    "060": {
      "%": 4.2307692,
      "v": 11.0
    },
    "061": {
      "%": 4.1884818,
      "v": 88.0
    },
    "062": {
      "%": 11.842105,
      "v": 9.0
    },
    "065": {
      "%": 1.4705882,
      "v": 1.0
    },
    "069": {
      "%": 3.5714285,
      "v": 27.0
    },
    "071": {
      "%": 3.8632987,
      "v": 26.0
    },
    "072": {
      "%": 7.8125,
      "v": 10.0
    },
    "074": {
      "%": 4.0462427,
      "v": 7.0
    },
    "075": {
      "%": 4.8715,
      "v": 127.0
    },
    "076": {
      "%": 3.6231885,
      "v": 5.0
    },
    "077": {
      "%": 2.3809524,
      "v": 17.0
    },
    "078": {
      "%": 4.058722,
      "v": 47.0
    },
    "079": {
      "%": 3.3299696,
      "v": 33.0
    },
    "081": {
      "%": 1.7543859,
      "v": 9.0
    },
    "082": {
      "%": 5.4461184,
      "v": 47.0
    },
    "086": {
      "%": 3.2214766,
      "v": 24.0
    },
    "111": {
      "%": 5.3221288,
      "v": 133.0
    },
    "090": {
      "%": 2.8257456,
      "v": 18.0
    },
    "091": {
      "%": 13.402323,
      "v": 7421.0
    },
    "097": {
      "%": 3.2697549,
      "v": 12.0
    },
    "098": {
      "%": 4.8379054,
      "v": 97.0
    },
    "099": {
      "%": 0.0,
      "v": 0.0
    },
    "102": {
      "%": 5.0035739,
      "v": 70.0
    },
    "103": {
      "%": 1.5686275,
      "v": 4.0
    },
    "105": {
      "%": 0.68337131,
      "v": 3.0
    },
    "106": {
      "%": 5.0598207,
      "v": 203.0
    },
    "108": {
      "%": 3.6971831,
      "v": 42.0
    },
    "109": {
      "%": 6.8639054,
      "v": 522.0
    },
    "139": {
      "%": 3.1872511,
      "v": 24.0
    },
    "140": {
      "%": 4.1350212,
      "v": 98.0
    },
    "142": {
      "%": 3.0100334,
      "v": 27.0
    },
    "143": {
      "%": 4.3699188,
      "v": 43.0
    },
    "145": {
      "%": 2.8205128,
      "v": 33.0
    },
    "146": {
      "%": 2.9867256,
      "v": 27.0
    },
    "153": {
      "%": 3.2417011,
      "v": 125.0
    },
    "148": {
      "%": 4.9036779,
      "v": 28.0
    },
    "149": {
      "%": 5.1948051,
      "v": 28.0
    },
    "151": {
      "%": 1.0526316,
      "v": 4.0
    },
    "152": {
      "%": 3.3182504,
      "v": 22.0
    },
    "165": {
      "%": 2.3215322,
      "v": 40.0
    },
    "167": {
      "%": 5.8859224,
      "v": 388.0
    },
    "169": {
      "%": 4.2357273,
      "v": 23.0
    },
    "170": {
      "%": 1.4440433,
      "v": 4.0
    },
    "171": {
      "%": 3.4534535,
      "v": 23.0
    },
    "172": {
      "%": 1.8666667,
      "v": 14.0
    },
    "176": {
      "%": 3.0219781,
      "v": 22.0
    },
    "177": {
      "%": 3.4722223,
      "v": 10.0
    },
    "178": {
      "%": 2.9527559,
      "v": 30.0
    },
    "179": {
      "%": 7.7068558,
      "v": 815.0
    },
    "181": {
      "%": 2.1201413,
      "v": 6.0
    },
    "182": {
      "%": 3.5814607,
      "v": 102.0
    },
    "186": {
      "%": 6.5086379,
      "v": 162.0
    },
    "202": {
      "%": 8.0397472,
      "v": 178.0
    },
    "204": {
      "%": 1.4,
      "v": 7.0
    },
    "205": {
      "%": 4.8421617,
      "v": 181.0
    },
    "208": {
      "%": 2.6622295,
      "v": 32.0
    },
    "211": {
      "%": 6.2759767,
      "v": 151.0
    },
    "213": {
      "%": 4.2462845,
      "v": 40.0
    },
    "214": {
      "%": 3.2110093,
      "v": 42.0
    },
    "216": {
      "%": 2.8571429,
      "v": 6.0
    },
    "217": {
      "%": 4.5454545,
      "v": 26.0
    },
    "218": {
      "%": 2.2988505,
      "v": 6.0
    },
    "224": {
      "%": 3.5233161,
      "v": 34.0
    },
    "226": {
      "%": 2.1381578,
      "v": 13.0
    },
    "230": {
      "%": 1.8372704,
      "v": 7.0
    },
    "231": {
      "%": 3.0927835,
      "v": 6.0
    },
    "232": {
      "%": 3.1715209,
      "v": 49.0
    },
    "233": {
      "%": 2.7570093,
      "v": 59.0
    },
    "235": {
      "%": 31.937799,
      "v": 267.0
    },
    "236": {
      "%": 2.8103044,
      "v": 12.0
    },
    "239": {
      "%": 1.9886364,
      "v": 7.0
    },
    "240": {
      "%": 4.0832992,
      "v": 100.0
    },
    "320": {
      "%": 3.3414834,
      "v": 41.0
    },
    "241": {
      "%": 3.8516405,
      "v": 27.0
    },
    "322": {
      "%": 3.3802817,
      "v": 36.0
    },
    "244": {
      "%": 6.9503546,
      "v": 49.0
    },
    "245": {
      "%": 7.0831499,
      "v": 161.0
    },
    "249": {
      "%": 3.6036036,
      "v": 52.0
    },
    "250": {
      "%": 2.5547445,
      "v": 7.0
    },
    "256": {
      "%": 3.2432432,
      "v": 6.0
    },
    "257": {
      "%": 9.4594593,
      "v": 182.0
    },
    "260": {
      "%": 3.9528432,
      "v": 57.0
    },
    "261": {
      "%": 3.9933443,
      "v": 24.0
    },
    "263": {
      "%": 2.570281,
      "v": 32.0
    },
    "265": {
      "%": 1.8957345,
      "v": 4.0
    },
    "271": {
      "%": 3.040834,
      "v": 35.0
    },
    "272": {
      "%": 3.7230258,
      "v": 157.0
    },
    "273": {
      "%": 2.6548672,
      "v": 12.0
    },
    "275": {
      "%": 2.1390374,
      "v": 8.0
    },
    "276": {
      "%": 4.0441175,
      "v": 33.0
    },
    "280": {
      "%": 3.654485,
      "v": 11.0
    },
    "284": {
      "%": 3.0150754,
      "v": 12.0
    },
    "285": {
      "%": 3.8115149,
      "v": 237.0
    },
    "286": {
      "%": 4.1159134,
      "v": 419.0
    },
    "287": {
      "%": 2.7663934,
      "v": 27.0
    },
    "288": {
      "%": 1.7994858,
      "v": 14.0
    },
    "290": {
      "%": 4.2984591,
      "v": 53.0
    },
    "291": {
      "%": 4.5908184,
      "v": 23.0
    },
    "295": {
      "%": 4.1666665,
      "v": 2.0
    },
    "297": {
      "%": 5.9245629,
      "v": 644.0
    },
    "300": {
      "%": 3.5335689,
      "v": 20.0
    },
    "301": {
      "%": 2.3255813,
      "v": 63.0
    },
    "304": {
      "%": 2.9585798,
      "v": 5.0
    },
    "305": {
      "%": 4.3608122,
      "v": 73.0
    },
    "312": {
      "%": 0.45045045,
      "v": 1.0
    },
    "316": {
      "%": 4.7524753,
      "v": 24.0
    },
    "317": {
      "%": 4.2492919,
      "v": 15.0
    },
    "318": {
      "%": 9.7560978,
      "v": 4.0
    },
    "398": {
      "%": 5.3682094,
      "v": 667.0
    },
    "399": {
      "%": 3.42556,
      "v": 26.0
    },
    "400": {
      "%": 2.7272727,
      "v": 27.0
    },
    "407": {
      "%": 1.7283951,
      "v": 7.0
    },
    "402": {
      "%": 3.2258065,
      "v": 42.0
    },
    "403": {
      "%": 1.875,
      "v": 9.0
    },
    "405": {
      "%": 4.599524,
      "v": 348.0
    },
    "408": {
      "%": 4.7440701,
      "v": 76.0
    },
    "410": {
      "%": 3.4122562,
      "v": 49.0
    },
    "416": {
      "%": 3.7267082,
      "v": 12.0
    },
    "417": {
      "%": 4.9180326,
      "v": 6.0
    },
    "418": {
      "%": 4.2473922,
      "v": 57.0
    },
    "420": {
      "%": 3.9230769,
      "v": 51.0
    },
    "421": {
      "%": 2.7777777,
      "v": 3.0
    },
    "422": {
      "%": 3.3916268,
      "v": 64.0
    },
    "423": {
      "%": 5.5857253,
      "v": 72.0
    },
    "425": {
      "%": 6.1696658,
      "v": 24.0
    },
    "426": {
      "%": 3.975265,
      "v": 45.0
    },
    "444": {
      "%": 4.7630334,
      "v": 201.0
    },
    "430": {
      "%": 3.8628473,
      "v": 89.0
    },
    "433": {
      "%": 2.9232643,
      "v": 24.0
    },
    "434": {
      "%": 4.4491525,
      "v": 84.0
    },
    "435": {
      "%": 4.7619047,
      "v": 8.0
    },
    "436": {
      "%": 2.6845639,
      "v": 4.0
    },
    "438": {
      "%": 4.2553191,
      "v": 2.0
    },
    "440": {
      "%": 4.6511626,
      "v": 12.0
    },
    "441": {
      "%": 2.4390244,
      "v": 18.0
    },
    "475": {
      "%": 2.4421594,
      "v": 19.0
    },
    "478": {
      "%": 7.4534163,
      "v": 84.0
    },
    "480": {
      "%": 1.7123288,
      "v": 5.0
    },
    "481": {
      "%": 5.5727553,
      "v": 36.0
    },
    "483": {
      "%": 1.5748031,
      "v": 2.0
    },
    "484": {
      "%": 1.5564202,
      "v": 8.0
    },
    "489": {
      "%": 0.51948053,
      "v": 2.0
    },
    "491": {
      "%": 6.143856,
      "v": 369.0
    },
    "494": {
      "%": 3.9097745,
      "v": 26.0
    },
    "495": {
      "%": 2.0979021,
      "v": 6.0
    },
    "498": {
      "%": 2.909091,
      "v": 8.0
    },
    "499": {
      "%": 4.8082776,
      "v": 79.0
    },
    "500": {
      "%": 6.6225166,
      "v": 40.0
    },
    "503": {
      "%": 2.4532709,
      "v": 21.0
    },
    "504": {
      "%": 2.0576131,
      "v": 5.0
    },
    "505": {
      "%": 5.9035277,
      "v": 82.0
    },
    "508": {
      "%": 3.1071656,
      "v": 49.0
    },
    "507": {
      "%": 3.8906415,
      "v": 37.0
    },
    "529": {
      "%": 8.3911676,
      "v": 133.0
    },
    "531": {
      "%": 5.231689,
      "v": 35.0
    },
    "535": {
      "%": 3.3366046,
      "v": 34.0
    },
    "536": {
      "%": 2.9666255,
      "v": 72.0
    },
    "538": {
      "%": 4.6647229,
      "v": 16.0
    },
    "541": {
      "%": 3.5,
      "v": 56.0
    },
    "543": {
      "%": 6.0175514,
      "v": 144.0
    },
    "545": {
      "%": 1.540832,
      "v": 20.0
    },
    "560": {
      "%": 3.4324942,
      "v": 60.0
    },
    "561": {
      "%": 2.4390244,
      "v": 4.0
    },
    "562": {
      "%": 5.2534561,
      "v": 57.0
    },
    "563": {
      "%": 4.2446942,
      "v": 34.0
    },
    "564": {
      "%": 7.606679,
      "v": 902.0
    },
    "309": {
      "%": 3.9256198,
      "v": 38.0
    },
    "576": {
      "%": 3.0075188,
      "v": 16.0
    },
    "577": {
      "%": 4.0586247,
      "v": 36.0
    },
    "578": {
      "%": 2.2680411,
      "v": 11.0
    },
    "445": {
      "%": 6.9121814,
      "v": 122.0
    },
    "580": {
      "%": 2.6732674,
      "v": 27.0
    },
    "581": {
      "%": 4.0974531,
      "v": 37.0
    },
    "599": {
      "%": 3.7558684,
      "v": 32.0
    },
    "583": {
      "%": 1.5873016,
      "v": 2.0
    },
    "854": {
      "%": 1.1494253,
      "v": 6.0
    },
    "584": {
      "%": 2.0547945,
      "v": 6.0
    },
    "588": {
      "%": 1.4749262,
      "v": 5.0
    },
    "592": {
      "%": 5.0761423,
      "v": 20.0
    },
    "593": {
      "%": 3.2749429,
      "v": 86.0
    },
    "595": {
      "%": 2.7918782,
      "v": 22.0
    },
    "598": {
      "%": 4.4550171,
      "v": 103.0
    },
    "601": {
      "%": 3.4369886,
      "v": 21.0
    },
    "604": {
      "%": 7.1561337,
      "v": 77.0
    },
    "607": {
      "%": 3.2894738,
      "v": 20.0
    },
    "608": {
      "%": 3.4682081,
      "v": 12.0
    },
    "609": {
      "%": 4.1349859,
      "v": 397.0
    },
    "611": {
      "%": 2.7303755,
      "v": 8.0
    },
    "638": {
      "%": 7.2623029,
      "v": 304.0
    },
    "614": {
      "%": 2.5341132,
      "v": 13.0
    },
    "615": {
      "%": 2.3191094,
      "v": 25.0
    },
    "616": {
      "%": 4.4554458,
      "v": 9.0
    },
    "619": {
      "%": 2.7290449,
      "v": 14.0
    },
    "620": {
      "%": 3.8374717,
      "v": 17.0
    },
    "623": {
      "%": 5.0438595,
      "v": 23.0
    },
    "624": {
      "%": 4.8780489,
      "v": 28.0
    },
    "625": {
      "%": 2.9629629,
      "v": 12.0
    },
    "626": {
      "%": 3.6904762,
      "v": 31.0
    },
    "630": {
      "%": 2.5316455,
      "v": 4.0
    },
    "631": {
      "%": 2.7450981,
      "v": 7.0
    },
    "635": {
      "%": 4.3035107,
      "v": 38.0
    },
    "636": {
      "%": 3.2820513,
      "v": 32.0
    },
    "678": {
      "%": 3.9134438,
      "v": 85.0
    },
    "710": {
      "%": 6.455399,
      "v": 220.0
    },
    "680": {
      "%": 5.1136365,
      "v": 99.0
    },
    "681": {
      "%": 2.4429967,
      "v": 15.0
    },
    "683": {
      "%": 5.7603688,
      "v": 25.0
    },
    "684": {
      "%": 4.1962852,
      "v": 183.0
    },
    "686": {
      "%": 3.1365314,
      "v": 17.0
    },
    "687": {
      "%": 2.8070176,
      "v": 8.0
    },
    "689": {
      "%": 1.4876033,
      "v": 9.0
    },
    "691": {
      "%": 2.3323615,
      "v": 8.0
    },
    "694": {
      "%": 5.319149,
      "v": 145.0
    },
    "697": {
      "%": 5.8035712,
      "v": 13.0
    },
    "698": {
      "%": 5.4789042,
      "v": 274.0
    },
    "700": {
      "%": 4.2525773,
      "v": 33.0
    },
    "702": {
      "%": 5.6356487,
      "v": 43.0
    },
    "704": {
      "%": 2.8653295,
      "v": 10.0
    },
    "707": {
      "%": 1.2594458,
      "v": 5.0
    },
    "729": {
      "%": 3.5353534,
      "v": 49.0
    },
    "732": {
      "%": 1.7921147,
      "v": 10.0
    },
    "734": {
      "%": 4.0962176,
      "v": 235.0
    },
    "736": {
      "%": 4.6242776,
      "v": 8.0
    },
    "790": {
      "%": 4.3851285,
      "v": 138.0
    },
    "738": {
      "%": 5.466238,
      "v": 17.0
    },
    "739": {
      "%": 3.8338659,
      "v": 24.0
    },
    "740": {
      "%": 4.7051172,
      "v": 217.0
    },
    "742": {
      "%": 0.68965518,
      "v": 1.0
    },
    "743": {
      "%": 5.1783195,
      "v": 257.0
    },
    "746": {
      "%": 2.200489,
      "v": 9.0
    },
    "747": {
      "%": 2.661597,
      "v": 7.0
    },
    "748": {
      "%": 2.0484171,
      "v": 11.0
    },
    "791": {
      "%": 2.8811524,
      "v": 24.0
    },
    "749": {
      "%": 4.263824,
      "v": 64.0
    },
    "751": {
      "%": 2.3809524,
      "v": 9.0
    },
    "753": {
      "%": 7.7397261,
      "v": 113.0
    },
    "755": {
      "%": 10.77348,
      "v": 39.0
    },
    "758": {
      "%": 3.504673,
      "v": 30.0
    },
    "759": {
      "%": 2.0588236,
      "v": 7.0
    },
    "761": {
      "%": 2.9814665,
      "v": 37.0
    },
    "762": {
      "%": 2.1352313,
      "v": 12.0
    },
    "765": {
      "%": 4.8414025,
      "v": 58.0
    },
    "766": {
      "%": 0.0,
      "v": 0.0
    },
    "768": {
      "%": 2.5440314,
      "v": 13.0
    },
    "771": {
      "%": 5.1724138,
      "v": 6.0
    },
    "777": {
      "%": 2.3293173,
      "v": 29.0
    },
    "778": {
      "%": 3.6827195,
      "v": 39.0
    },
    "781": {
      "%": 5.6629834,
      "v": 41.0
    },
    "783": {
      "%": 2.9612756,
      "v": 26.0
    },
    "831": {
      "%": 7.9726653,
      "v": 35.0
    },
    "832": {
      "%": 4.1958041,
      "v": 18.0
    },
    "833": {
      "%": 3.6734693,
      "v": 9.0
    },
    "834": {
      "%": 4.927536,
      "v": 34.0
    },
    "837": {
      "%": 6.9761581,
      "v": 1384.0
    },
    "844": {
      "%": 3.515625,
      "v": 9.0
    },
    "845": {
      "%": 3.1042128,
      "v": 14.0
    },
    "846": {
      "%": 2.8868361,
      "v": 25.0
    },
    "848": {
      "%": 2.300406,
      "v": 17.0
    },
    "849": {
      "%": 2.6315789,
      "v": 10.0
    },
    "850": {
      "%": 5.3691278,
      "v": 16.0
    },
    "851": {
      "%": 5.0530572,
      "v": 100.0
    },
    "853": {
      "%": 8.3629894,
      "v": 1598.0
    },
    "857": {
      "%": 3.4802785,
      "v": 15.0
    },
    "858": {
      "%": 5.7622504,
      "v": 127.0
    },
    "859": {
      "%": 5.1490517,
      "v": 19.0
    },
    "886": {
      "%": 4.0316772,
      "v": 56.0
    },
    "887": {
      "%": 3.576159,
      "v": 27.0
    },
    "889": {
      "%": 2.102102,
      "v": 7.0
    },
    "890": {
      "%": 5.3333335,
      "v": 8.0
    },
    "892": {
      "%": 4.1958041,
      "v": 12.0
    },
    "893": {
      "%": 4.0091639,
      "v": 35.0
    },
    "895": {
      "%": 4.3885312,
      "v": 75.0
    },
    "785": {
      "%": 2.7397261,
      "v": 14.0
    },
    "905": {
      "%": 5.8161955,
      "v": 362.0
    },
    "908": {
      "%": 4.4976883,
      "v": 107.0
    },
    "092": {
      "%": 6.7053308,
      "v": 844.0
    },
    "915": {
      "%": 3.3993275,
      "v": 91.0
    },
    "918": {
      "%": 1.1904762,
      "v": 4.0
    },
    "921": {
      "%": 3.4398034,
      "v": 14.0
    },
    "922": {
      "%": 7.4766355,
      "v": 24.0
    },
    "924": {
      "%": 3.1042128,
      "v": 14.0
    },
    "925": {
      "%": 3.2258065,
      "v": 15.0
    },
    "927": {
      "%": 6.230032,
      "v": 117.0
    },
    "931": {
      "%": 4.1879468,
      "v": 41.0
    },
    "934": {
      "%": 4.0404038,
      "v": 16.0
    },
    "935": {
      "%": 3.3898306,
      "v": 16.0
    },
    "936": {
      "%": 3.3301618,
      "v": 35.0
    },
    "941": {
      "%": 1.8181819,
      "v": 1.0
    },
    "946": {
      "%": 2.7713625,
      "v": 24.0
    },
    "976": {
      "%": 3.806735,
      "v": 26.0
    },
    "977": {
      "%": 5.0566697,
      "v": 58.0
    },
    "980": {
      "%": 5.3222656,
      "v": 109.0
    },
    "981": {
      "%": 3.3222592,
      "v": 10.0
    },
    "989": {
      "%": 2.6066351,
      "v": 22.0
    },
    "992": {
      "%": 3.2386646,
      "v": 65.0
    }
  }
}