{
  "original_file": "Finland_2017.csv",
  "year": 2017,
  "country": "FI",
  "var": "ed_isced_3to5",
  "data": {
    "020": {
      "%": 54.132442,
      "v": 7447.0
    },
    "005": {
      "%": 53.881336,
      "v": 4359.0
    },
    "009": {
      "%": 56.4347,
      "v": 1184.0
    },
    "010": {
      "%": 54.537971,
      "v": 5300.0
    },
    "016": {
      "%": 52.711864,
      "v": 3732.0
    },
    "018": {
      "%": 54.964718,
      "v": 2181.0
    },
    "019": {
      "%": 53.663116,
      "v": 1714.0
    },
    "035": {
      "%": 44.306931,
      "v": 179.0
    },
    "043": {
      "%": 53.063725,
      "v": 433.0
    },
    "046": {
      "%": 52.572346,
      "v": 654.0
    },
    "047": {
      "%": 56.424244,
      "v": 931.0
    },
    "049": {
      "%": 38.896076,
      "v": 87508.0
    },
    "050": {
      "%": 52.55138,
      "v": 5242.0
    },
    "051": {
      "%": 51.760654,
      "v": 4057.0
    },
    "052": {
      "%": 52.714287,
      "v": 1107.0
    },
    "060": {
      "%": 50.852272,
      "v": 1074.0
    },
    "061": {
      "%": 54.664886,
      "v": 8197.0
    },
    "062": {
      "%": 44.255318,
      "v": 208.0
    },
    "065": {
      "%": 48.564594,
      "v": 203.0
    },
    "069": {
      "%": 53.160675,
      "v": 3120.0
    },
    "071": {
      "%": 58.387798,
      "v": 3216.0
    },
    "072": {
      "%": 58.224854,
      "v": 492.0
    },
    "074": {
      "%": 48.313492,
      "v": 487.0
    },
    "075": {
      "%": 56.011051,
      "v": 9933.0
    },
    "076": {
      "%": 51.927616,
      "v": 660.0
    },
    "077": {
      "%": 55.377735,
      "v": 2353.0
    },
    "078": {
      "%": 47.509785,
      "v": 3520.0
    },
    "079": {
      "%": 54.751797,
      "v": 3353.0
    },
    "081": {
      "%": 49.092312,
      "v": 1271.0
    },
    "082": {
      "%": 56.39336,
      "v": 4450.0
    },
    "086": {
      "%": 56.226471,
      "v": 3883.0
    },
    "111": {
      "%": 55.008904,
      "v": 9269.0
    },
    "090": {
      "%": 51.256119,
      "v": 1571.0
    },
    "091": {
      "%": 40.213661,
      "v": 221790.0
    },
    "097": {
      "%": 50.351406,
      "v": 1003.0
    },
    "098": {
      "%": 53.84457,
      "v": 10469.0
    },
    "099": {
      "%": 49.966011,
      "v": 735.0
    },
    "102": {
      "%": 54.217834,
      "v": 4724.0
    },
    "103": {
      "%": 55.311543,
      "v": 1083.0
    },
    "105": {
      "%": 54.420803,
      "v": 1151.0
    },
    "106": {
      "%": 51.977386,
      "v": 20411.0
    },
    "108": {
      "%": 56.777611,
      "v": 4930.0
    },
    "109": {
      "%": 52.844509,
      "v": 30356.0
    },
    "139": {
      "%": 56.279434,
      "v": 4302.0
    },
    "140": {
      "%": 58.030437,
      "v": 10601.0
    },
    "142": {
      "%": 53.573265,
      "v": 3126.0
    },
    "143": {
      "%": 55.669083,
      "v": 3378.0
    },
    "145": {
      "%": 56.18219,
      "v": 5489.0
    },
    "146": {
      "%": 54.017761,
      "v": 2494.0
    },
    "153": {
      "%": 55.169514,
      "v": 13116.0
    },
    "148": {
      "%": 56.14502,
      "v": 3376.0
    },
    "149": {
      "%": 49.48431,
      "v": 2255.0
    },
    "151": {
      "%": 50.335571,
      "v": 900.0
    },
    "152": {
      "%": 56.348591,
      "v": 2179.0
    },
    "165": {
      "%": 55.544258,
      "v": 7649.0
    },
    "167": {
      "%": 54.569366,
      "v": 35684.0
    },
    "169": {
      "%": 55.71106,
      "v": 2468.0
    },
    "170": {
      "%": 50.052742,
      "v": 1898.0
    },
    "171": {
      "%": 57.440758,
      "v": 2424.0
    },
    "172": {
      "%": 51.904999,
      "v": 2098.0
    },
    "176": {
      "%": 54.15406,
      "v": 2327.0
    },
    "177": {
      "%": 53.121098,
      "v": 851.0
    },
    "178": {
      "%": 54.08952,
      "v": 3009.0
    },
    "179": {
      "%": 51.870884,
      "v": 61176.0
    },
    "181": {
      "%": 55.611603,
      "v": 882.0
    },
    "182": {
      "%": 57.515907,
      "v": 10396.0
    },
    "186": {
      "%": 51.027321,
      "v": 17931.0
    },
    "202": {
      "%": 48.845795,
      "v": 13098.0
    },
    "204": {
      "%": 53.365746,
      "v": 1427.0
    },
    "205": {
      "%": 56.720428,
      "v": 17724.0
    },
    "208": {
      "%": 56.770576,
      "v": 5773.0
    },
    "211": {
      "%": 52.388714,
      "v": 13181.0
    },
    "213": {
      "%": 52.17659,
      "v": 2541.0
    },
    "214": {
      "%": 55.741699,
      "v": 5490.0
    },
    "216": {
      "%": 50.904606,
      "v": 619.0
    },
    "217": {
      "%": 55.86729,
      "v": 2509.0
    },
    "218": {
      "%": 55.564995,
      "v": 654.0
    },
    "224": {
      "%": 51.202473,
      "v": 3811.0
    },
    "226": {
      "%": 54.375175,
      "v": 1945.0
    },
    "230": {
      "%": 54.204277,
      "v": 1141.0
    },
    "231": {
      "%": 53.122253,
      "v": 604.0
    },
    "232": {
      "%": 56.573776,
      "v": 6476.0
    },
    "233": {
      "%": 54.419769,
      "v": 7400.0
    },
    "235": {
      "%": 35.080391,
      "v": 2771.0
    },
    "236": {
      "%": 52.076767,
      "v": 1818.0
    },
    "239": {
      "%": 53.883972,
      "v": 1096.0
    },
    "240": {
      "%": 56.426762,
      "v": 10255.0
    },
    "320": {
      "%": 58.926727,
      "v": 3997.0
    },
    "241": {
      "%": 58.216579,
      "v": 3989.0
    },
    "322": {
      "%": 49.932274,
      "v": 2949.0
    },
    "244": {
      "%": 52.698627,
      "v": 6991.0
    },
    "245": {
      "%": 48.914001,
      "v": 14458.0
    },
    "249": {
      "%": 57.104336,
      "v": 4871.0
    },
    "250": {
      "%": 52.906635,
      "v": 901.0
    },
    "256": {
      "%": 48.215588,
      "v": 662.0
    },
    "257": {
      "%": 44.479111,
      "v": 13829.0
    },
    "260": {
      "%": 55.445007,
      "v": 5127.0
    },
    "261": {
      "%": 59.91116,
      "v": 3237.0
    },
    "263": {
      "%": 56.91655,
      "v": 4024.0
    },
    "265": {
      "%": 51.773048,
      "v": 511.0
    },
    "271": {
      "%": 54.534046,
      "v": 3476.0
    },
    "272": {
      "%": 53.838398,
      "v": 20822.0
    },
    "273": {
      "%": 58.280159,
      "v": 1918.0
    },
    "275": {
      "%": 55.428814,
      "v": 1312.0
    },
    "276": {
      "%": 55.472874,
      "v": 6411.0
    },
    "280": {
      "%": 51.333694,
      "v": 943.0
    },
    "284": {
      "%": 52.094627,
      "v": 1057.0
    },
    "285": {
      "%": 55.311039,
      "v": 25536.0
    },
    "286": {
      "%": 55.21336,
      "v": 40033.0
    },
    "287": {
      "%": 50.505569,
      "v": 2947.0
    },
    "288": {
      "%": 50.074158,
      "v": 2701.0
    },
    "290": {
      "%": 58.064518,
      "v": 4356.0
    },
    "291": {
      "%": 51.719128,
      "v": 1068.0
    },
    "295": {
      "%": 46.126762,
      "v": 131.0
    },
    "297": {
      "%": 54.705116,
      "v": 54977.0
    },
    "300": {
      "%": 51.243137,
      "v": 1587.0
    },
    "301": {
      "%": 57.065582,
      "v": 10233.0
    },
    "304": {
      "%": 52.781067,
      "v": 446.0
    },
    "305": {
      "%": 59.843124,
      "v": 7782.0
    },
    "312": {
      "%": 50.0,
      "v": 573.0
    },
    "316": {
      "%": 53.315994,
      "v": 2050.0
    },
    "317": {
      "%": 55.016487,
      "v": 1168.0
    },
    "318": {
      "%": 45.909092,
      "v": 101.0
    },
    "398": {
      "%": 52.269962,
      "v": 53284.0
    },
    "399": {
      "%": 51.229763,
      "v": 3291.0
    },
    "400": {
      "%": 54.217876,
      "v": 3882.0
    },
    "407": {
      "%": 50.173161,
      "v": 1159.0
    },
    "402": {
      "%": 55.688477,
      "v": 4562.0
    },
    "403": {
      "%": 55.872547,
      "v": 1508.0
    },
    "405": {
      "%": 52.781742,
      "v": 32930.0
    },
    "408": {
      "%": 54.622135,
      "v": 6411.0
    },
    "410": {
      "%": 55.774361,
      "v": 8157.0
    },
    "416": {
      "%": 52.625298,
      "v": 1323.0
    },
    "417": {
      "%": 53.710461,
      "v": 883.0
    },
    "418": {
      "%": 50.6814,
      "v": 8851.0
    },
    "420": {
      "%": 55.304016,
      "v": 4666.0
    },
    "421": {
      "%": 49.249249,
      "v": 328.0
    },
    "422": {
      "%": 55.445644,
      "v": 5605.0
    },
    "423": {
      "%": 50.991428,
      "v": 7972.0
    },
    "425": {
      "%": 50.467846,
      "v": 3398.0
    },
    "426": {
      "%": 58.220425,
      "v": 5758.0
    },
    "444": {
      "%": 52.089008,
      "v": 20272.0
    },
    "430": {
      "%": 54.893188,
      "v": 7606.0
    },
    "433": {
      "%": 54.169842,
      "v": 3553.0
    },
    "434": {
      "%": 50.67244,
      "v": 6556.0
    },
    "435": {
      "%": 45.921452,
      "v": 304.0
    },
    "436": {
      "%": 55.668705,
      "v": 820.0
    },
    "438": {
      "%": 51.506023,
      "v": 171.0
    },
    "440": {
      "%": 55.489452,
      "v": 2052.0
    },
    "441": {
      "%": 52.378651,
      "v": 2169.0
    },
    "475": {
      "%": 51.869358,
      "v": 2414.0
    },
    "478": {
      "%": 47.355793,
      "v": 4737.0
    },
    "480": {
      "%": 53.400955,
      "v": 895.0
    },
    "481": {
      "%": 54.583553,
      "v": 4168.0
    },
    "483": {
      "%": 53.418308,
      "v": 461.0
    },
    "484": {
      "%": 49.705013,
      "v": 1348.0
    },
    "489": {
      "%": 50.140846,
      "v": 890.0
    },
    "491": {
      "%": 54.350445,
      "v": 25261.0
    },
    "494": {
      "%": 56.645615,
      "v": 3857.0
    },
    "495": {
      "%": 56.048676,
      "v": 783.0
    },
    "498": {
      "%": 59.694656,
      "v": 1173.0
    },
    "499": {
      "%": 51.093143,
      "v": 7899.0
    },
    "500": {
      "%": 52.531406,
      "v": 4140.0
    },
    "503": {
      "%": 56.069973,
      "v": 3718.0
    },
    "504": {
      "%": 54.887676,
      "v": 904.0
    },
    "505": {
      "%": 52.608643,
      "v": 8692.0
    },
    "508": {
      "%": 56.55983,
      "v": 5100.0
    },
    "507": {
      "%": 51.0158,
      "v": 2712.0
    },
    "529": {
      "%": 53.209019,
      "v": 8589.0
    },
    "531": {
      "%": 53.733593,
      "v": 2497.0
    },
    "535": {
      "%": 58.376553,
      "v": 4840.0
    },
    "536": {
      "%": 53.38525,
      "v": 14327.0
    },
    "538": {
      "%": 56.452457,
      "v": 2161.0
    },
    "541": {
      "%": 55.205837,
      "v": 4841.0
    },
    "543": {
      "%": 49.948742,
      "v": 16566.0
    },
    "545": {
      "%": 47.777229,
      "v": 3869.0
    },
    "560": {
      "%": 54.901669,
      "v": 7342.0
    },
    "561": {
      "%": 50.265957,
      "v": 567.0
    },
    "562": {
      "%": 54.296627,
      "v": 4265.0
    },
    "563": {
      "%": 56.873051,
      "v": 3463.0
    },
    "564": {
      "%": 50.790405,
      "v": 83247.0
    },
    "309": {
      "%": 58.294392,
      "v": 3493.0
    },
    "576": {
      "%": 49.962879,
      "v": 1346.0
    },
    "577": {
      "%": 53.860359,
      "v": 4667.0
    },
    "578": {
      "%": 55.447536,
      "v": 1654.0
    },
    "445": {
      "%": 49.050289,
      "v": 6301.0
    },
    "580": {
      "%": 53.782452,
      "v": 2403.0
    },
    "581": {
      "%": 55.656189,
      "v": 3134.0
    },
    "599": {
      "%": 55.39679,
      "v": 4691.0
    },
    "583": {
      "%": 59.698025,
      "v": 514.0
    },
    "854": {
      "%": 56.281567,
      "v": 1783.0
    },
    "584": {
      "%": 51.841358,
      "v": 1098.0
    },
    "588": {
      "%": 50.948334,
      "v": 779.0
    },
    "592": {
      "%": 53.772987,
      "v": 1696.0
    },
    "593": {
      "%": 57.761799,
      "v": 9239.0
    },
    "595": {
      "%": 54.342873,
      "v": 2146.0
    },
    "598": {
      "%": 48.401127,
      "v": 7901.0
    },
    "601": {
      "%": 54.178593,
      "v": 1893.0
    },
    "604": {
      "%": 48.940372,
      "v": 7436.0
    },
    "607": {
      "%": 57.354855,
      "v": 2203.0
    },
    "608": {
      "%": 50.380848,
      "v": 926.0
    },
    "609": {
      "%": 54.740639,
      "v": 39595.0
    },
    "611": {
      "%": 54.570499,
      "v": 2179.0
    },
    "638": {
      "%": 49.296967,
      "v": 20405.0
    },
    "614": {
      "%": 54.455116,
      "v": 1644.0
    },
    "615": {
      "%": 54.582905,
      "v": 3710.0
    },
    "616": {
      "%": 57.54364,
      "v": 923.0
    },
    "619": {
      "%": 52.360516,
      "v": 1342.0
    },
    "620": {
      "%": 52.092831,
      "v": 1257.0
    },
    "623": {
      "%": 52.289513,
      "v": 1062.0
    },
    "624": {
      "%": 52.986774,
      "v": 2324.0
    },
    "625": {
      "%": 57.050056,
      "v": 1493.0
    },
    "626": {
      "%": 54.313942,
      "v": 2474.0
    },
    "630": {
      "%": 56.255043,
      "v": 697.0
    },
    "631": {
      "%": 55.970573,
      "v": 989.0
    },
    "635": {
      "%": 54.465408,
      "v": 3031.0
    },
    "636": {
      "%": 52.490143,
      "v": 3594.0
    },
    "678": {
      "%": 58.12466,
      "v": 11722.0
    },
    "710": {
      "%": 49.120731,
      "v": 11620.0
    },
    "680": {
      "%": 53.186275,
      "v": 10850.0
    },
    "681": {
      "%": 55.676022,
      "v": 1746.0
    },
    "683": {
      "%": 52.732918,
      "v": 1698.0
    },
    "684": {
      "%": 52.696136,
      "v": 17786.0
    },
    "686": {
      "%": 53.928192,
      "v": 1517.0
    },
    "687": {
      "%": 50.753109,
      "v": 775.0
    },
    "689": {
      "%": 53.617573,
      "v": 1660.0
    },
    "691": {
      "%": 50.725273,
      "v": 1154.0
    },
    "694": {
      "%": 54.19693,
      "v": 13133.0
    },
    "697": {
      "%": 54.222973,
      "v": 642.0
    },
    "698": {
      "%": 55.676277,
      "v": 29004.0
    },
    "700": {
      "%": 53.525784,
      "v": 2429.0
    },
    "702": {
      "%": 54.628922,
      "v": 2142.0
    },
    "704": {
      "%": 55.25005,
      "v": 2773.0
    },
    "707": {
      "%": 57.439445,
      "v": 1162.0
    },
    "729": {
      "%": 55.083405,
      "v": 4524.0
    },
    "732": {
      "%": 56.685322,
      "v": 1823.0
    },
    "734": {
      "%": 51.914913,
      "v": 23356.0
    },
    "736": {
      "%": 53.143227,
      "v": 820.0
    },
    "790": {
      "%": 54.194008,
      "v": 11397.0
    },
    "738": {
      "%": 52.952911,
      "v": 1327.0
    },
    "739": {
      "%": 51.813473,
      "v": 1600.0
    },
    "740": {
      "%": 55.489254,
      "v": 16831.0
    },
    "742": {
      "%": 56.593407,
      "v": 515.0
    },
    "743": {
      "%": 55.56741,
      "v": 28645.0
    },
    "746": {
      "%": 55.814583,
      "v": 2059.0
    },
    "747": {
      "%": 53.518948,
      "v": 692.0
    },
    "748": {
      "%": 56.66827,
      "v": 2354.0
    },
    "791": {
      "%": 56.900303,
      "v": 2614.0
    },
    "749": {
      "%": 56.355125,
      "v": 9750.0
    },
    "751": {
      "%": 55.781544,
      "v": 1481.0
    },
    "753": {
      "%": 47.642635,
      "v": 7791.0
    },
    "755": {
      "%": 47.26125,
      "v": 2321.0
    },
    "758": {
      "%": 58.809235,
      "v": 4356.0
    },
    "759": {
      "%": 50.141003,
      "v": 889.0
    },
    "761": {
      "%": 51.839729,
      "v": 3959.0
    },
    "762": {
      "%": 56.056339,
      "v": 1990.0
    },
    "765": {
      "%": 56.211464,
      "v": 4923.0
    },
    "766": {
      "%": 45.054947,
      "v": 41.0
    },
    "768": {
      "%": 51.111111,
      "v": 1196.0
    },
    "771": {
      "%": 52.397259,
      "v": 459.0
    },
    "777": {
      "%": 58.44463,
      "v": 4201.0
    },
    "778": {
      "%": 56.804356,
      "v": 3548.0
    },
    "781": {
      "%": 50.257584,
      "v": 1756.0
    },
    "783": {
      "%": 54.582073,
      "v": 3252.0
    },
    "831": {
      "%": 52.34021,
      "v": 2080.0
    },
    "832": {
      "%": 58.38419,
      "v": 2009.0
    },
    "833": {
      "%": 52.183098,
      "v": 741.0
    },
    "834": {
      "%": 55.538433,
      "v": 2883.0
    },
    "837": {
      "%": 50.005501,
      "v": 100027.0
    },
    "844": {
      "%": 55.031227,
      "v": 793.0
    },
    "845": {
      "%": 58.494209,
      "v": 1515.0
    },
    "846": {
      "%": 56.923759,
      "v": 2561.0
    },
    "848": {
      "%": 55.084106,
      "v": 2194.0
    },
    "849": {
      "%": 51.694584,
      "v": 1327.0
    },
    "850": {
      "%": 52.773457,
      "v": 1018.0
    },
    "851": {
      "%": 56.912594,
      "v": 10275.0
    },
    "853": {
      "%": 49.243309,
      "v": 81379.0
    },
    "857": {
      "%": 56.858501,
      "v": 1314.0
    },
    "858": {
      "%": 49.398598,
      "v": 15360.0
    },
    "859": {
      "%": 55.729847,
      "v": 2558.0
    },
    "886": {
      "%": 54.603699,
      "v": 5966.0
    },
    "887": {
      "%": 52.676865,
      "v": 2204.0
    },
    "889": {
      "%": 56.355019,
      "v": 1308.0
    },
    "890": {
      "%": 49.099525,
      "v": 518.0
    },
    "892": {
      "%": 55.647484,
      "v": 1547.0
    },
    "893": {
      "%": 50.341576,
      "v": 3095.0
    },
    "895": {
      "%": 58.186638,
      "v": 7900.0
    },
    "785": {
      "%": 56.822575,
      "v": 1470.0
    },
    "905": {
      "%": 49.971767,
      "v": 28319.0
    },
    "908": {
      "%": 56.589279,
      "v": 10018.0
    },
    "911": {
      "%": NaN,
      "v": NaN
    },
    "092": {
      "%": 46.857693,
      "v": 85952.0
    },
    "915": {
      "%": 55.90398,
      "v": 10340.0
    },
    "918": {
      "%": 58.104736,
      "v": 1165.0
    },
    "921": {
      "%": 50.212994,
      "v": 943.0
    },
    "922": {
      "%": 51.118118,
      "v": 1783.0
    },
    "924": {
      "%": 54.933235,
      "v": 1481.0
    },
    "925": {
      "%": 56.964855,
      "v": 1783.0
    },
    "927": {
      "%": 50.933662,
      "v": 11947.0
    },
    "931": {
      "%": 55.05122,
      "v": 3117.0
    },
    "934": {
      "%": 54.942436,
      "v": 1384.0
    },
    "935": {
      "%": 55.995678,
      "v": 1555.0
    },
    "936": {
      "%": 54.356915,
      "v": 3250.0
    },
    "941": {
      "%": 50.134769,
      "v": 186.0
    },
    "946": {
      "%": 51.494591,
      "v": 2808.0
    },
    "976": {
      "%": 54.885994,
      "v": 2022.0
    },
    "977": {
      "%": 55.453407,
      "v": 6635.0
    },
    "980": {
      "%": 54.136684,
      "v": 13918.0
    },
    "981": {
      "%": 58.597176,
      "v": 1203.0
    },
    "989": {
      "%": 56.610504,
      "v": 2856.0
    },
    "992": {
      "%": 57.034908,
      "v": 9133.0
    }
  }
}